{"ChIJJ_gRlzJ444kRCODusUoKKAY": {"geometry": {"location": {"lat": 42.3571725, "lng": -71.1465322}, "viewport": {"northeast": {"lat": 42.3585214302915, "lng": -71.14460294999999}, "southwest": {"lat": 42.3558234697085, "lng": -71.14846154999998}}}, "icon": "https://maps.gstatic.com/mapfiles/place_api/icons/geocode-71.png", "id": "df09ea0b02082ad482efbf87a77c57e18dfcf793", "name": "25-53 Guest St", "place_id": "ChIJJ_gRlzJ444kRCODusUoKKAY", "reference": "ChIJJ_gRlzJ444kRCODusUoKKAY", "scope": "GOOGLE", "types": ["route"], "vicinity": "Boston"}, "ChIJVa48lzJ444kR4eF6Tj4ZuI4": {"geometry": {"location": {"lat": 42.3568253, "lng": -71.1465226}, "viewport": {"northeast": {"lat": 42.35834173029149, "lng": -71.1451326197085}, "southwest": {"lat": 42.3556437697085, "lng": -71.14783058029151}}}, "icon": "https://maps.gstatic.com/mapfiles/place_api/icons/generic_business-71.png", "id": "ca8a99180123519a0b6c95343075dcce5303bcc0", "name": "WAAF", "opening_hours": {"open_now": true}, "place_id": "ChIJVa48lzJ444kR4eF6Tj4ZuI4", "plus_code": {"compound_code": "9V43+P9 Boston, Massachusetts, United States", "global_code": "87JC9V43+P9"}, "rating": 4.9, "reference": "ChIJVa48lzJ444kR4eF6Tj4ZuI4", "scope": "GOOGLE", "types": ["point_of_interest", "establishment"], "user_ratings_total": 7, "vicinity": "20 Guest Street, Boston"}, "ChIJVa48lzJ444kRuHV2LtsUT34": {"geometry": {"location": {"lat": 42.3568253, "lng": -71.1465226}, "viewport": {"northeast": {"lat": 42.35834173029149, "lng": -71.1451326197085}, "southwest": {"lat": 42.3556437697085, "lng": -71.14783058029151}}}, "icon": "https://maps.gstatic.com/mapfiles/place_api/icons/generic_business-71.png", "id": "a6157f91e8156c8958ed86ace876585b2f2034b5", "name": "WEEI Sports Radio Network", "opening_hours": {"open_now": true}, "photos": [{"height": 642, "html_attributions": ["<a href=\"https://maps.google.com/maps/contrib/110735629091698230949/photos\">WEEI Sports Radio Network</a>"], "photo_reference": "CmRaAAAAr-I1FOIBCcZXf8I9alsKaSKYnNnI9At3ZS42sOfxiz9Z5TvSDrxAns6Bp8XLdDUMXFpMeo1ZbkVbQA9N0klKmmDlDeTXPO29OMT-QMu1PhpmLfixo_vPfzfmjNF-pYLwEhCBGkciRmx17ljN16O0agcjGhTgfrlrM64XWzquD46bVbX3bFN9EQ", "width": 642}], "place_id": "ChIJVa48lzJ444kRuHV2LtsUT34", "plus_code": {"compound_code": "9V43+P9 Boston, Massachusetts, United States", "global_code": "87JC9V43+P9"}, "rating": 3, "reference": "ChIJVa48lzJ444kRuHV2LtsUT34", "scope": "GOOGLE", "types": ["point_of_interest", "establishment"], "user_ratings_total": 6, "vicinity": "20 Guest Street # 300, Brighton"}, "ChIJvaFsYKB544kRwu6gwQIFQxM": {"geometry": {"location": {"lat": 42.3568253, "lng": -71.1465226}, "viewport": {"northeast": {"lat": 42.35834173029149, "lng": -71.1451326197085}, "southwest": {"lat": 42.3556437697085, "lng": -71.14783058029151}}}, "icon": "https://maps.gstatic.com/mapfiles/place_api/icons/generic_business-71.png", "id": "e24e288b7fd3ce105d0917df8944b073eef3f152", "name": "Pro Sports Orthopedics", "opening_hours": {"open_now": false}, "photos": [{"height": 2620, "html_attributions": ["<a href=\"https://maps.google.com/maps/contrib/104226012770742589180/photos\">Stephanie Thomas</a>"], "photo_reference": "CmRaAAAAiw9U2nbYNOp5zDC6uNlulOKjAouPh1FAbpK2yFsnydNbBUvlharwRZYwbbjJC0Rv9P1jqmYJyz-VD7FFTCXGVv7SJD50KtUUb9B9aMFSSeaWCurSegZ_csMwaUmqMpEYEhDtoexU1Y6QuUhkYymPCk-KGhR2rhcXwB42mFlZzTeMSAAi7AoWOw", "width": 4656}], "place_id": "ChIJvaFsYKB544kRwu6gwQIFQxM", "plus_code": {"compound_code": "9V43+P9 Boston, Massachusetts, United States", "global_code": "87JC9V43+P9"}, "rating": 3.1, "reference": "ChIJvaFsYKB544kRwu6gwQIFQxM", "scope": "GOOGLE", "types": ["doctor", "health", "point_of_interest", "establishment"], "user_ratings_total": 9, "vicinity": "20 Guest Street #225, Boston"}, "ChIJVa48lzJ444kRrx3kPZvrg3s": {"geometry": {"location": {"lat": 42.3571064, "lng": -71.146655}, "viewport": {"northeast": {"lat": 42.3584952802915, "lng": -71.1452962697085}, "southwest": {"lat": 42.3557973197085, "lng": -71.1479942302915}}}, "icon": "https://maps.gstatic.com/mapfiles/place_api/icons/generic_business-71.png", "id": "690caef97da2d5fdb0a266941deca6a3d07867e5", "name": "Corporate Chefs Inc", "place_id": "ChIJVa48lzJ444kRrx3kPZvrg3s", "plus_code": {"compound_code": "9V43+R8 Boston, Massachusetts, United States", "global_code": "87JC9V43+R8"}, "reference": "ChIJVa48lzJ444kRrx3kPZvrg3s", "scope": "GOOGLE", "types": ["point_of_interest", "food", "establishment"], "vicinity": "20 Guest Street, Brighton"}, "ChIJuxH6lzJ444kRIuPAZW7QUQo": {"geometry": {"location": {"lat": 42.3568253, "lng": -71.1465226}, "viewport": {"northeast": {"lat": 42.35834173029149, "lng": -71.1451326197085}, "southwest": {"lat": 42.3556437697085, "lng": -71.14783058029151}}}, "icon": "https://maps.gstatic.com/mapfiles/place_api/icons/generic_business-71.png", "id": "c443a19b22f7d15b4bb5bf242b1c47c1751cdc8f", "name": "New Balance at 20 Guest St Hubway Station", "opening_hours": {"open_now": true}, "photos": [{"height": 2448, "html_attributions": ["<a href=\"https://maps.google.com/maps/contrib/114634565822659148185/photos\">mir09 com</a>"], "photo_reference": "CmRaAAAAe6xRO6FCx49UE_l3iggCkxrp15ae5zHAdKZR2a0DtNH4qM0iImtqHezykCtFGAwxpm4NSjK2VI3oyHn8nnJmVZfSwx6v_f3PqK126QYXP_8dhpIxGxU8VPVLR0hVFwOVEhDEfWfWUs_l4mmNdKMmfzH7GhSNrjFt2IHRdHqBANzOGwiLotmvRw", "width": 3264}], "place_id": "ChIJuxH6lzJ444kRIuPAZW7QUQo", "plus_code": {"compound_code": "9V43+P9 Boston, Massachusetts, United States", "global_code": "87JC9V43+P9"}, "rating": 4.5, "reference": "ChIJuxH6lzJ444kRIuPAZW7QUQo", "scope": "GOOGLE", "types": ["point_of_interest", "establishment"], "user_ratings_total": 4, "vicinity": "20 Guest Street, Boston"}, "ChIJA8bOjzJ444kR-giHG28WnbI": {"geometry": {"location": {"lat": 42.3568253, "lng": -71.1465226}, "viewport": {"northeast": {"lat": 42.35834173029149, "lng": -71.1451326197085}, "southwest": {"lat": 42.3556437697085, "lng": -71.14783058029151}}}, "icon": "https://maps.gstatic.com/mapfiles/place_api/icons/generic_business-71.png", "id": "1037b4bfbe1c21062c4e558187499fb0f48fda0e", "name": "PBS Distribution", "opening_hours": {"open_now": true}, "photos": [{"height": 2988, "html_attributions": ["<a href=\"https://maps.google.com/maps/contrib/100122473379728298534/photos\">Matthew Valentinas</a>"], "photo_reference": "CmRaAAAAoEIi0ovlD9r1jNm703YpJyr47-ja9uLEibif52SSVaCIl95onV5nrehrkP28yyWjs3X5tDFfb-hEvYKci_82qtcomzAycaQu-JknbSIoAq0eO6B3ik5qoBOXRbqKSsQMEhCgiCpHDkYhRwXL6sY_iH4kGhTxonLeUhpAQ_dC6ypTXQtvKxmugA", "width": 5312}], "place_id": "ChIJA8bOjzJ444kR-giHG28WnbI", "plus_code": {"compound_code": "9V43+P9 Boston, Massachusetts, United States", "global_code": "87JC9V43+P9"}, "rating": 3, "reference": "ChIJA8bOjzJ444kR-giHG28WnbI", "scope": "GOOGLE", "types": ["point_of_interest", "establishment"], "user_ratings_total": 2, "vicinity": "10 Guest Street, Boston"}, "ChIJOWB3bM1544kRq_PzYGX5QAo": {"geometry": {"location": {"lat": 42.3568253, "lng": -71.1465226}, "viewport": {"northeast": {"lat": 42.35834173029149, "lng": -71.1451326197085}, "southwest": {"lat": 42.3556437697085, "lng": -71.14783058029151}}}, "icon": "https://maps.gstatic.com/mapfiles/place_api/icons/shopping-71.png", "id": "76eeddae23d9200cc29789b37df1afc780b19d97", "name": "Major League Lacrosse", "opening_hours": {"open_now": true}, "place_id": "ChIJOWB3bM1544kRq_PzYGX5QAo", "plus_code": {"compound_code": "9V43+P9 Boston, Massachusetts, United States", "global_code": "87JC9V43+P9"}, "reference": "ChIJOWB3bM1544kRq_PzYGX5QAo", "scope": "GOOGLE", "types": ["store", "point_of_interest", "establishment"], "vicinity": "20 Guest Street, Brighton"}, "ChIJA8bOjzJ444kRZOMMAnSBTA4": {"geometry": {"location": {"lat": 42.3568253, "lng": -71.1465226}, "viewport": {"northeast": {"lat": 42.35834173029149, "lng": -71.1451326197085}, "southwest": {"lat": 42.3556437697085, "lng": -71.14783058029151}}}, "icon": "https://maps.gstatic.com/mapfiles/place_api/icons/generic_business-71.png", "id": "080c29d23d45ec0676cddec1f6b96c663d8bc879", "name": "Global Novations", "place_id": "ChIJA8bOjzJ444kRZOMMAnSBTA4", "plus_code": {"compound_code": "9V43+P9 Boston, Massachusetts, United States", "global_code": "87JC9V43+P9"}, "reference": "ChIJA8bOjzJ444kRZOMMAnSBTA4", "scope": "GOOGLE", "types": ["point_of_interest", "establishment"], "vicinity": "10 Guest Street #300, Brighton"}, "ChIJVa48lzJ444kR7PvZrs65C9c": {"geometry": {"location": {"lat": 42.3568253, "lng": -71.1465226}, "viewport": {"northeast": {"lat": 42.35834173029149, "lng": -71.1451326197085}, "southwest": {"lat": 42.3556437697085, "lng": -71.14783058029151}}}, "icon": "https://maps.gstatic.com/mapfiles/place_api/icons/generic_business-71.png", "id": "a17f19240c7561c7eddee8318358d9fd13ff9bed", "name": "WRKO", "place_id": "ChIJVa48lzJ444kR7PvZrs65C9c", "plus_code": {"compound_code": "9V43+P9 Boston, Massachusetts, United States", "global_code": "87JC9V43+P9"}, "reference": "ChIJVa48lzJ444kR7PvZrs65C9c", "scope": "GOOGLE", "types": ["point_of_interest", "establishment"], "vicinity": "20 Guest Street # 300, Brighton"}, "ChIJ46cKYzJ444kR14h6QpXx-o4": {"geometry": {"location": {"lat": 42.3568253, "lng": -71.1465226}, "viewport": {"northeast": {"lat": 42.35834173029149, "lng": -71.1451326197085}, "southwest": {"lat": 42.3556437697085, "lng": -71.14783058029151}}}, "icon": "https://maps.gstatic.com/mapfiles/place_api/icons/generic_business-71.png", "id": "c3e608ab35cab3df1d311ba588ee6aabaadebd4a", "name": "Boston Baroque", "photos": [{"height": 853, "html_attributions": ["<a href=\"https://maps.google.com/maps/contrib/116140650320618102455/photos\">Julie&#39;s bites</a>"], "photo_reference": "CmRaAAAAR8hqW2J1fZdz9OmosZhLTT-gBjbzs-1P5h3eUc_6ONvwPtCxTve0runUJ5oYGTxUYgu_1rXojt3vvuYcfvp6sk6QQgh7RZAERKmgFPnnrzFJODwQfyaLVjrl96EH_R2oEhChlOkHk8TKB_u9GyixJYliGhSmey03WhEVpThd7Jpm5EFaCEx1eQ", "width": 1200}], "place_id": "ChIJ46cKYzJ444kR14h6QpXx-o4", "plus_code": {"compound_code": "9V43+P9 Boston, Massachusetts, United States", "global_code": "87JC9V43+P9"}, "reference": "ChIJ46cKYzJ444kR14h6QpXx-o4", "scope": "GOOGLE", "types": ["point_of_interest", "establishment"], "vicinity": "10 Guest Street, Brighton"}, "ChIJb97pTgB544kRbabF0LdZA3o": {"geometry": {"location": {"lat": 42.3568253, "lng": -71.1465226}, "viewport": {"northeast": {"lat": 42.35834173029149, "lng": -71.1451326197085}, "southwest": {"lat": 42.3556437697085, "lng": -71.14783058029151}}}, "icon": "https://maps.gstatic.com/mapfiles/place_api/icons/generic_business-71.png", "id": "15487514e1d11638aae6f98c9ceed29d95a6470e", "name": "Dr. L Douglas Dolgov", "place_id": "ChIJb97pTgB544kRbabF0LdZA3o", "plus_code": {"compound_code": "9V43+P9 Boston, Massachusetts, United States", "global_code": "87JC9V43+P9"}, "reference": "ChIJb97pTgB544kRbabF0LdZA3o", "scope": "GOOGLE", "types": ["doctor", "health", "point_of_interest", "establishment"], "vicinity": "20 Guest Street Suite 225, Brighton"}, "ChIJMSO8YTJ444kRqMS24zRewLc": {"geometry": {"location": {"lat": 42.3568253, "lng": -71.1465226}, "viewport": {"northeast": {"lat": 42.35834173029149, "lng": -71.1451326197085}, "southwest": {"lat": 42.3556437697085, "lng": -71.14783058029151}}}, "icon": "https://maps.gstatic.com/mapfiles/place_api/icons/generic_business-71.png", "id": "7c288355543f652080738c45aa3ac055fe5a60ee", "name": "NE Shoulder & Elbow Center.", "place_id": "ChIJMSO8YTJ444kRqMS24zRewLc", "plus_code": {"compound_code": "9V43+P9 Boston, Massachusetts, United States", "global_code": "87JC9V43+P9"}, "reference": "ChIJMSO8YTJ444kRqMS24zRewLc", "scope": "GOOGLE", "types": ["health", "point_of_interest", "establishment"], "vicinity": "20 Guest Street #225, Boston"}, "ChIJMSO8YTJ444kRAFVIkmRQylc": {"geometry": {"location": {"lat": 42.3568253, "lng": -71.1465226}, "viewport": {"northeast": {"lat": 42.35834173029149, "lng": -71.1451326197085}, "southwest": {"lat": 42.3556437697085, "lng": -71.14783058029151}}}, "icon": "https://maps.gstatic.com/mapfiles/place_api/icons/generic_business-71.png", "id": "4b9619c9dc98fb1646cdc15668f12d2b6a819000", "name": "ASF-Peak Health", "opening_hours": {"open_now": true}, "photos": [{"height": 683, "html_attributions": ["<a href=\"https://maps.google.com/maps/contrib/111665432643176132532/photos\">ASF-Peak Health</a>"], "photo_reference": "CmRaAAAAIBH1Af3fOpLI59HXxd48sEJ49hmjic_6aUoWBeRwxNaaeSmJ-By4K9BxskWioNFWP9TvUcgI1r1ZzhhM3U4E5_Gohie-N0j9b6CAq1bo7kHDzS9bBWHOyXwB0f4WSQ0tEhA2i77TeWyBpDvEZUYoooyDGhSaUfnmljbVIAey4g9uCd-oHGnZtA", "width": 960}], "place_id": "ChIJMSO8YTJ444kRAFVIkmRQylc", "plus_code": {"compound_code": "9V43+P9 Boston, Massachusetts, United States", "global_code": "87JC9V43+P9"}, "reference": "ChIJMSO8YTJ444kRAFVIkmRQylc", "scope": "GOOGLE", "types": ["health", "point_of_interest", "establishment"], "vicinity": "20 Guest Street #225b, Boston"}, "ChIJMyO8YTJ444kRE9fv1hTERTk": {"geometry": {"location": {"lat": 42.3568253, "lng": -71.1465226}, "viewport": {"northeast": {"lat": 42.35834173029149, "lng": -71.1451326197085}, "southwest": {"lat": 42.3556437697085, "lng": -71.14783058029151}}}, "icon": "https://maps.gstatic.com/mapfiles/place_api/icons/generic_business-71.png", "id": "d1a67b838c229172914ce56f398575aeed4a1e75", "name": "bc parking", "place_id": "ChIJMyO8YTJ444kRE9fv1hTERTk", "plus_code": {"compound_code": "9V43+P9 Boston, Massachusetts, United States", "global_code": "87JC9V43+P9"}, "reference": "ChIJMyO8YTJ444kRE9fv1hTERTk", "scope": "GOOGLE", "types": ["stadium", "point_of_interest", "establishment"], "vicinity": "20 Guest Street, Brighton"}, "ChIJNWYInzJ444kRDTVVS54Nfdw": {"geometry": {"location": {"lat": 42.3568253, "lng": -71.1465226}, "viewport": {"northeast": {"lat": 42.35834173029149, "lng": -71.1451326197085}, "southwest": {"lat": 42.3556437697085, "lng": -71.14783058029151}}}, "icon": "https://maps.gstatic.com/mapfiles/place_api/icons/generic_business-71.png", "id": "cdfc375e13fea79c88937500d7f26f84ed950282", "name": "90+ Cellars", "opening_hours": {"open_now": true}, "photos": [{"height": 1124, "html_attributions": ["<a href=\"https://maps.google.com/maps/contrib/101380405371520559146/photos\">90+ Cellars</a>"], "photo_reference": "CmRaAAAACyxGae8q8b15CyRgWUJ3lwvrFxfrQolpXjCQMin9NZt0yzLfzBKsdCq9U42fk42LUij2J-5H11nG01R0_hRcBacGf6iqpkcdKMJ3Zom0VCE9KP7EuRPSOJZg5ENb3FdVEhCSq6thwYeSm_iTi1CAodY4GhTy6wBO7bphoPMK7SjIlNBX7WToFw", "width": 2000}], "place_id": "ChIJNWYInzJ444kRDTVVS54Nfdw", "plus_code": {"compound_code": "9V43+P9 Boston, Massachusetts, United States", "global_code": "87JC9V43+P9"}, "rating": 5, "reference": "ChIJNWYInzJ444kRDTVVS54Nfdw", "scope": "GOOGLE", "types": ["point_of_interest", "food", "establishment"], "user_ratings_total": 2, "vicinity": "20 Guest Street, Boston"}, "ChIJ12uCYjJ444kRxnx6T3OZns4": {"geometry": {"location": {"lat": 42.3568253, "lng": -71.1465226}, "viewport": {"northeast": {"lat": 42.35834173029149, "lng": -71.1451326197085}, "southwest": {"lat": 42.3556437697085, "lng": -71.14783058029151}}}, "icon": "https://maps.gstatic.com/mapfiles/place_api/icons/generic_business-71.png", "id": "0870b9af9b69d488f5ee1707dd9020ad281c0be7", "name": "Dr. John T. Hester", "place_id": "ChIJ12uCYjJ444kRxnx6T3OZns4", "plus_code": {"compound_code": "9V43+P9 Boston, Massachusetts, United States", "global_code": "87JC9V43+P9"}, "reference": "ChIJ12uCYjJ444kRxnx6T3OZns4", "scope": "GOOGLE", "types": ["doctor", "health", "point_of_interest", "establishment"], "vicinity": "20 Guest Street Suite 225, Brighton"}, "ChIJYRPZiDJ444kRM0PLKu7TCxc": {"geometry": {"location": {"lat": 42.3570557, "lng": -71.1463433}, "viewport": {"northeast": {"lat": 42.3583490802915, "lng": -71.14462221970851}, "southwest": {"lat": 42.3556511197085, "lng": -71.14732018029152}}}, "icon": "https://maps.gstatic.com/mapfiles/place_api/icons/generic_business-71.png", "id": "1f271b53d50e6abc2f5533793ba953a51362320a", "name": "NB Fitness Club, LLC", "opening_hours": {"open_now": true}, "photos": [{"height": 427, "html_attributions": ["<a href=\"https://maps.google.com/maps/contrib/116277248215550485853/photos\">NB Fitness Club, LLC</a>"], "photo_reference": "CmRaAAAAKKMA1PSxb9qa6BsqSA3cunkmJ5bDu8FAKQpoEo1zS7BprV1NeRPxItMWa_naxb7TX1aQR2aHM1vOnnXovhsgHmQRcDN_VYVs8oKngBA_839ayMDJBhSSpUUzDoikJRPkEhAAsvNCxDCcJ1pe3_fzcQZUGhQlxwGRz5vVqR6ePkIYWxs6oDJ1zQ", "width": 640}], "place_id": "ChIJYRPZiDJ444kRM0PLKu7TCxc", "plus_code": {"compound_code": "9V43+RF Boston, Massachusetts, United States", "global_code": "87JC9V43+RF"}, "rating": 4.1, "reference": "ChIJYRPZiDJ444kRM0PLKu7TCxc", "scope": "GOOGLE", "types": ["gym", "health", "point_of_interest", "establishment"], "user_ratings_total": 14, "vicinity": "40 Life Street, Brighton"}, "ChIJ__8voDJ444kRwom5PIVF7yQ": {"geometry": {"location": {"lat": 42.3568253, "lng": -71.1465226}, "viewport": {"northeast": {"lat": 42.35834173029149, "lng": -71.1451326197085}, "southwest": {"lat": 42.3556437697085, "lng": -71.14783058029151}}}, "icon": "https://maps.gstatic.com/mapfiles/place_api/icons/generic_business-71.png", "id": "c995c83f2d9e6c71fd7e5d4d411b376b7f525c41", "name": "latitude beverage", "opening_hours": {"open_now": false}, "place_id": "ChIJ__8voDJ444kRwom5PIVF7yQ", "plus_code": {"compound_code": "9V43+P9 Boston, Massachusetts, United States", "global_code": "87JC9V43+P9"}, "reference": "ChIJ__8voDJ444kRwom5PIVF7yQ", "scope": "GOOGLE", "types": ["point_of_interest", "establishment"], "vicinity": "20 Guest Street, Boston"}, "ChIJGzE9DS1l44kRoOhiASS_fHg": {"geometry": {"location": {"lat": 42.3600825, "lng": -71.0588801}, "viewport": {"northeast": {"lat": 42.40081989999999, "lng": -70.749455}, "southwest": {"lat": 42.22788, "lng": -71.191113}}}, "icon": "https://maps.gstatic.com/mapfiles/place_api/icons/geocode-71.png", "id": "06755c25d2b34d13942a4713971756a55b870ced", "name": "Boston", "photos": [{"height": 3024, "html_attributions": ["<a href=\"https://maps.google.com/maps/contrib/104670289779338733432/photos\">Natalia Zalucean</a>"], "photo_reference": "CmRaAAAA72AfSvXveuoVsy5Lwzcv53-F56xKpIevixkcgvvBQktDpikaCyPIqRv-JS8ComTMGdmWfK3K2IU0R_frif7QLcrPul3dCJj-0S5UPC2JKXvhRZbkhZnbr_h6k6xoBCOPEhBRlPqZtm6LGWrHSKelJ9YRGhRHmxTcE9Woo7TGl1CHcol4zF_rfA", "width": 4032}], "place_id": "ChIJGzE9DS1l44kRoOhiASS_fHg", "reference": "ChIJGzE9DS1l44kRoOhiASS_fHg", "scope": "GOOGLE", "types": ["locality", "political"], "vicinity": "Boston"}, "ChIJVa48lzJ444kR1b8Q5bN5TUE": {"geometry": {"location": {"lat": 42.3568253, "lng": -71.1465226}, "viewport": {"northeast": {"lat": 42.35834173029149, "lng": -71.1451326197085}, "southwest": {"lat": 42.3556437697085, "lng": -71.14783058029151}}}, "icon": "https://maps.gstatic.com/mapfiles/place_api/icons/generic_business-71.png", "id": "7665304a9466a39ca5ebb2a89f2758318defaa11", "name": "B V Development", "place_id": "ChIJVa48lzJ444kR1b8Q5bN5TUE", "plus_code": {"compound_code": "9V43+P9 Boston, Massachusetts, United States", "global_code": "87JC9V43+P9"}, "reference": "ChIJVa48lzJ444kR1b8Q5bN5TUE", "scope": "GOOGLE", "types": ["general_contractor", "point_of_interest", "establishment"], "vicinity": "20 Guest Street # 100, Brighton"}, "ChIJha88lzJ444kRXzYN_KWdXgA": {"geometry": {"location": {"lat": 42.3568253, "lng": -71.1465226}, "viewport": {"northeast": {"lat": 42.35834173029149, "lng": -71.1451326197085}, "southwest": {"lat": 42.3556437697085, "lng": -71.14783058029151}}}, "icon": "https://maps.gstatic.com/mapfiles/place_api/icons/generic_business-71.png", "id": "6dc8ab8388ab9d30fc82ced959a878c40715684a", "name": "Star 937", "place_id": "ChIJha88lzJ444kRXzYN_KWdXgA", "plus_code": {"compound_code": "9V43+P9 Boston, Massachusetts, United States", "global_code": "87JC9V43+P9"}, "reference": "ChIJha88lzJ444kRXzYN_KWdXgA", "scope": "GOOGLE", "types": ["point_of_interest", "establishment"], "vicinity": "20 Guest Street, Brighton"}, "ChIJHUXxlDJ444kR_l-f7u74AME": {"geometry": {"location": {"lat": 42.35681510000001, "lng": -71.1465889}, "viewport": {"northeast": {"lat": 42.3583407802915, "lng": -71.1451966697085}, "southwest": {"lat": 42.3556428197085, "lng": -71.1478946302915}}}, "icon": "https://maps.gstatic.com/mapfiles/place_api/icons/generic_business-71.png", "id": "0d1a42524de979de0e1e983bf13a58c2b74753af", "name": "Modern Barre | Brighton", "place_id": "ChIJHUXxlDJ444kR_l-f7u74AME", "plus_code": {"compound_code": "9V43+P9 Boston, Massachusetts, United States", "global_code": "87JC9V43+P9"}, "reference": "ChIJHUXxlDJ444kR_l-f7u74AME", "scope": "GOOGLE", "types": ["point_of_interest", "establishment"], "vicinity": "25 Guest Street, Brighton"}, "ChIJ46cKYzJ444kRH-NVWVhs5-8": {"geometry": {"location": {"lat": 42.3568253, "lng": -71.1465226}, "viewport": {"northeast": {"lat": 42.35834173029149, "lng": -71.1451326197085}, "southwest": {"lat": 42.3556437697085, "lng": -71.14783058029151}}}, "icon": "https://maps.gstatic.com/mapfiles/place_api/icons/generic_business-71.png", "id": "1c4d419db71c42126ccdfc03e1f8681705451cb8", "name": "Novation Group Vms", "place_id": "ChIJ46cKYzJ444kRH-NVWVhs5-8", "plus_code": {"compound_code": "9V43+P9 Boston, Massachusetts, United States", "global_code": "87JC9V43+P9"}, "reference": "ChIJ46cKYzJ444kRH-NVWVhs5-8", "scope": "GOOGLE", "types": ["point_of_interest", "establishment"], "vicinity": "10 Guest Street # 300, Brighton"}, "ChIJ__8voDJ444kRy__rVhVzRTc": {"geometry": {"location": {"lat": 42.3568253, "lng": -71.1465226}, "viewport": {"northeast": {"lat": 42.35834173029149, "lng": -71.1451326197085}, "southwest": {"lat": 42.3556437697085, "lng": -71.14783058029151}}}, "icon": "https://maps.gstatic.com/mapfiles/place_api/icons/generic_business-71.png", "id": "5f4bd267ce183683520e6e5e7b8ecd3a5042199e", "name": "earthshaker wine", "place_id": "ChIJ__8voDJ444kRy__rVhVzRTc", "plus_code": {"compound_code": "9V43+P9 Boston, Massachusetts, United States", "global_code": "87JC9V43+P9"}, "reference": "ChIJ__8voDJ444kRy__rVhVzRTc", "scope": "GOOGLE", "types": ["point_of_interest", "food", "establishment"], "vicinity": "20 Guest Street, Boston"}, "ChIJ12uCYjJ444kR6ePTLi-3K9E": {"geometry": {"location": {"lat": 42.3568253, "lng": -71.1465226}, "viewport": {"northeast": {"lat": 42.35834173029149, "lng": -71.1451326197085}, "southwest": {"lat": 42.3556437697085, "lng": -71.14783058029151}}}, "icon": "https://maps.gstatic.com/mapfiles/place_api/icons/cafe-71.png", "id": "bd82b38040293496cd4578a6a56b7521973b9dba", "name": "Brighton Landing Cafe", "opening_hours": {"open_now": false}, "photos": [{"height": 2448, "html_attributions": ["<a href=\"https://maps.google.com/maps/contrib/118253647470076820130/photos\">Neamah Islam</a>"], "photo_reference": "CmRaAAAAVziJvfj-OY0RjGEP1HMaqK7yj5itWcG7S6ZwWLQyifj4zWUyfj3gAnHhVBPFHZ5PetAbx6c6gJ-LZNhzj3EHvmQ2u8EsaVU8yFYSgizxVFfrT-c4etdEZiAIwaLf50cfEhCDlZSWX1k69RjGOCZGTSTjGhRLfgE0JDv7YuYBm4Vz-4zKpU956g", "width": 3264}], "place_id": "ChIJ12uCYjJ444kR6ePTLi-3K9E", "plus_code": {"compound_code": "9V43+P9 Boston, Massachusetts, United States", "global_code": "87JC9V43+P9"}, "price_level": 1, "rating": 4, "reference": "ChIJ12uCYjJ444kR6ePTLi-3K9E", "scope": "GOOGLE", "types": ["cafe", "point_of_interest", "food", "establishment"], "user_ratings_total": 5, "vicinity": "20 Guest Street, Boston"}, "ChIJ__8voDJ444kRpz4HqExDpKw": {"geometry": {"location": {"lat": 42.3568253, "lng": -71.1465226}, "viewport": {"northeast": {"lat": 42.35834173029149, "lng": -71.1451326197085}, "southwest": {"lat": 42.3556437697085, "lng": -71.14783058029151}}}, "icon": "https://maps.gstatic.com/mapfiles/place_api/icons/generic_business-71.png", "id": "6b09f1ff795c9f16942b506edd17e31c24525a4f", "name": "Mija Sangria", "place_id": "ChIJ__8voDJ444kRpz4HqExDpKw", "plus_code": {"compound_code": "9V43+P9 Boston, Massachusetts, United States", "global_code": "87JC9V43+P9"}, "reference": "ChIJ__8voDJ444kRpz4HqExDpKw", "scope": "GOOGLE", "types": ["point_of_interest", "establishment"], "vicinity": "20 Guest Street, Boston"}, "ChIJ__8voDJ444kRYOu-FGGSmPk": {"geometry": {"location": {"lat": 42.3568253, "lng": -71.1465226}, "viewport": {"northeast": {"lat": 42.35834173029149, "lng": -71.1451326197085}, "southwest": {"lat": 42.3556437697085, "lng": -71.14783058029151}}}, "icon": "https://maps.gstatic.com/mapfiles/place_api/icons/shopping-71.png", "id": "2182d1bfe979d79d63da2641d90911d1e6d627cd", "name": "lila wine", "place_id": "ChIJ__8voDJ444kRYOu-FGGSmPk", "plus_code": {"compound_code": "9V43+P9 Boston, Massachusetts, United States", "global_code": "87JC9V43+P9"}, "reference": "ChIJ__8voDJ444kRYOu-FGGSmPk", "scope": "GOOGLE", "types": ["liquor_store", "store", "point_of_interest", "establishment"], "vicinity": "20 Guest Street, Boston"}, "ChIJTbpHkDJ444kRisHMcGkcy9U": {"geometry": {"location": {"lat": 42.3568253, "lng": -71.1465226}, "viewport": {"northeast": {"lat": 42.35834173029149, "lng": -71.1451326197085}, "southwest": {"lat": 42.3556437697085, "lng": -71.14783058029151}}}, "icon": "https://maps.gstatic.com/mapfiles/place_api/icons/generic_business-71.png", "id": "7ecaa1dfd73941476cfa737ead97fec4cd880050", "name": "Strong Fitnesd", "place_id": "ChIJTbpHkDJ444kRisHMcGkcy9U", "plus_code": {"compound_code": "9V43+P9 Boston, Massachusetts, United States", "global_code": "87JC9V43+P9"}, "reference": "ChIJTbpHkDJ444kRisHMcGkcy9U", "scope": "GOOGLE", "types": ["gym", "health", "point_of_interest", "establishment"], "vicinity": "20 Guest Street, Boston"}, "ChIJ__8voDJ444kRacVc2NET0M8": {"geometry": {"location": {"lat": 42.3568253, "lng": -71.1465226}, "viewport": {"northeast": {"lat": 42.35834173029149, "lng": -71.1451326197085}, "southwest": {"lat": 42.3556437697085, "lng": -71.14783058029151}}}, "icon": "https://maps.gstatic.com/mapfiles/place_api/icons/generic_business-71.png", "id": "9f0af1f903eedbe73790d5c77a3820418e368262", "name": "NB Development Group", "place_id": "ChIJ__8voDJ444kRacVc2NET0M8", "plus_code": {"compound_code": "9V43+P9 Boston, Massachusetts, United States", "global_code": "87JC9V43+P9"}, "reference": "ChIJ__8voDJ444kRacVc2NET0M8", "scope": "GOOGLE", "types": ["general_contractor", "point_of_interest", "establishment"], "vicinity": "20 Guest Street, Boston"}, "ChIJiSk_kDJ444kRlp3TUZYlY_s": {"geometry": {"location": {"lat": 42.35690040000001, "lng": -71.1466871}, "viewport": {"northeast": {"lat": 42.3583856302915, "lng": -71.14527661970848}, "southwest": {"lat": 42.3556876697085, "lng": -71.14797458029149}}}, "icon": "https://maps.gstatic.com/mapfiles/place_api/icons/generic_business-71.png", "id": "ac24019be1f473427f7d6d6075a33cda6227d535", "name": "Guest Street Parking", "photos": [{"height": 3492, "html_attributions": ["<a href=\"https://maps.google.com/maps/contrib/106375293128327515352/photos\">Craig Johnson</a>"], "photo_reference": "CmRaAAAAJAxeO5dZ_SE8Gp7l-c0UwRftVypZHfeVOsFg746646h8Y3lRAnLmqrF5LShip0AY6AHj3TLPicBsvm8uoFnmrucrGUBH4znan546r1n8jVGftNOsYZU-6EnUN4yOlnXoEhAWUu4CluXSDY9DDfMN_-50GhTPVJE0BsrHw-1XXXE9v3rP0zvRAA", "width": 4656}], "place_id": "ChIJiSk_kDJ444kRlp3TUZYlY_s", "plus_code": {"compound_code": "9V43+Q8 Boston, Massachusetts, United States", "global_code": "87JC9V43+Q8"}, "reference": "ChIJiSk_kDJ444kRlp3TUZYlY_s", "scope": "GOOGLE", "types": ["parking", "point_of_interest", "establishment"], "vicinity": "20 Guest Street, Brighton"}, "ChIJvfDNkDJ444kRrtVHwR7KbOc": {"geometry": {"location": {"lat": 42.35704519999999, "lng": -71.14646549999999}, "viewport": {"northeast": {"lat": 42.3584514802915, "lng": -71.14510251970849}, "southwest": {"lat": 42.3557535197085, "lng": -71.1478004802915}}}, "icon": "https://maps.gstatic.com/mapfiles/place_api/icons/generic_business-71.png", "id": "a153566d2a9caaded18e9b214f64793be78ff0e7", "name": "WGBH Parking", "opening_hours": {"open_now": false}, "place_id": "ChIJvfDNkDJ444kRrtVHwR7KbOc", "plus_code": {"compound_code": "9V43+RC Boston, Massachusetts, United States", "global_code": "87JC9V43+RC"}, "rating": 3.5, "reference": "ChIJvfDNkDJ444kRrtVHwR7KbOc", "scope": "GOOGLE", "types": ["parking", "point_of_interest", "establishment"], "user_ratings_total": 2, "vicinity": "15 Guest Street, Boston"}}