{"ChIJXWewfYl544kRFjXu42Key2M": {"geometry": {"location": {"lat": 42.3357055, "lng": -71.10080959999999}, "viewport": {"northeast": {"lat": 42.3370761302915, "lng": -71.09947731970848}, "southwest": {"lat": 42.3343781697085, "lng": -71.1021752802915}}}, "icon": "https://maps.gstatic.com/mapfiles/place_api/icons/geocode-71.png", "id": "539d177d232bdf1aa6a13631722c494e6406576f", "name": "631-649 Huntington Ave", "place_id": "ChIJXWewfYl544kRFjXu42Key2M", "reference": "ChIJXWewfYl544kRFjXu42Key2M", "scope": "GOOGLE", "types": ["route"], "vicinity": "Boston"}, "ChIJO5U9YYl544kRQT2DouNwsHU": {"geometry": {"location": {"lat": 42.3357189, "lng": -71.1015243}, "viewport": {"northeast": {"lat": 42.3370432302915, "lng": -71.10004956970849}, "southwest": {"lat": 42.3343452697085, "lng": -71.10274753029151}}}, "icon": "https://maps.gstatic.com/mapfiles/place_api/icons/school-71.png", "id": "3b2e7e502e8d25b9212ce683d7e8a8806026124d", "name": "FXB Harvard School of Public Health", "place_id": "ChIJO5U9YYl544kRQT2DouNwsHU", "plus_code": {"compound_code": "8VPX+79 Boston, Massachusetts, United States", "global_code": "87JC8VPX+79"}, "reference": "ChIJO5U9YYl544kRQT2DouNwsHU", "scope": "GOOGLE", "types": ["school", "point_of_interest", "establishment"], "vicinity": "651 Huntington Avenue, Boston"}, "ChIJ_fHzRIl544kRgaJBXtx1gD4": {"geometry": {"location": {"lat": 42.3355611, "lng": -71.1016065}, "viewport": {"northeast": {"lat": 42.33685508029149, "lng": -71.10022366970851}, "southwest": {"lat": 42.33415711970849, "lng": -71.10292163029152}}}, "icon": "https://maps.gstatic.com/mapfiles/place_api/icons/generic_business-71.png", "id": "31c79cf800d9cc36752530f2fe0d191eedc16676", "name": "Hauser Russ B MD", "place_id": "ChIJ_fHzRIl544kRgaJBXtx1gD4", "plus_code": {"compound_code": "8VPX+69 Boston, Massachusetts, United States", "global_code": "87JC8VPX+69"}, "reference": "ChIJ_fHzRIl544kRgaJBXtx1gD4", "scope": "GOOGLE", "types": ["doctor", "health", "point_of_interest", "establishment"], "vicinity": "665 Huntington Avenue, Boston"}, "ChIJjWEcZ4l544kRAV9wm4RK5uA": {"geometry": {"location": {"lat": 42.3355611, "lng": -71.1016066}, "viewport": {"northeast": {"lat": 42.3368550302915, "lng": -71.10022376970849}, "southwest": {"lat": 42.3341570697085, "lng": -71.1029217302915}}}, "icon": "https://maps.gstatic.com/mapfiles/place_api/icons/school-71.png", "id": "ce45efa8c835319a5f7af78378394e5bc863e516", "name": "HSPH", "place_id": "ChIJjWEcZ4l544kRAV9wm4RK5uA", "plus_code": {"compound_code": "8VPX+69 Boston, Massachusetts, United States", "global_code": "87JC8VPX+69"}, "rating": 5, "reference": "ChIJjWEcZ4l544kRAV9wm4RK5uA", "scope": "GOOGLE", "types": ["school", "point_of_interest", "establishment"], "user_ratings_total": 1, "vicinity": "665 Huntington Avenue, Boston"}, "ChIJJZU9YYl544kRPiERfqKUD3c": {"geometry": {"location": {"lat": 42.3357189, "lng": -71.1015243}, "viewport": {"northeast": {"lat": 42.3370432302915, "lng": -71.10004956970849}, "southwest": {"lat": 42.3343452697085, "lng": -71.10274753029151}}}, "icon": "https://maps.gstatic.com/mapfiles/place_api/icons/generic_business-71.png", "id": "28719a9558a7d3bf2ca4a6d81308b4222fe05b22", "name": "Jennifer Leaning, MD, SMH", "place_id": "ChIJJZU9YYl544kRPiERfqKUD3c", "plus_code": {"compound_code": "8VPX+79 Boston, Massachusetts, United States", "global_code": "87JC8VPX+79"}, "reference": "ChIJJZU9YYl544kRPiERfqKUD3c", "scope": "GOOGLE", "types": ["doctor", "health", "point_of_interest", "establishment"], "vicinity": "7, 651 Huntington Avenue, Boston"}, "ChIJPYBB2xh544kRSon2hw-2RVg": {"geometry": {"location": {"lat": 42.3357189, "lng": -71.1015243}, "viewport": {"northeast": {"lat": 42.33706788029149, "lng": -71.10017531970848}, "southwest": {"lat": 42.33436991970849, "lng": -71.1028732802915}}}, "icon": "https://maps.gstatic.com/mapfiles/place_api/icons/lodging-71.png", "id": "f3f59e005d3b9ea25f6a9f4386ebfd36c4a9bcab", "name": "apart hotel", "place_id": "ChIJPYBB2xh544kRSon2hw-2RVg", "plus_code": {"compound_code": "8VPX+79 Boston, Massachusetts, United States", "global_code": "87JC8VPX+79"}, "reference": "ChIJPYBB2xh544kRSon2hw-2RVg", "scope": "GOOGLE", "types": ["lodging", "point_of_interest", "establishment"], "vicinity": "651 Huntington Avenue, Boston"}, "ChIJGzE9DS1l44kRoOhiASS_fHg": {"geometry": {"location": {"lat": 42.3600825, "lng": -71.0588801}, "viewport": {"northeast": {"lat": 42.40081989999999, "lng": -70.749455}, "southwest": {"lat": 42.22788, "lng": -71.191113}}}, "icon": "https://maps.gstatic.com/mapfiles/place_api/icons/geocode-71.png", "id": "06755c25d2b34d13942a4713971756a55b870ced", "name": "Boston", "photos": [{"height": 3024, "html_attributions": ["<a href=\"https://maps.google.com/maps/contrib/104670289779338733432/photos\">Natalia Zalucean</a>"], "photo_reference": "CmRaAAAAJRtXlkaT9IN5uk15MnYWZ1gvmyFfBLruSALEgGLdrFObbiMdZ2EXbF9vgHkpoKvnf5fyCazWfvDunkjXN_7Gede_gUPM1iORJZvqJ2KFMdOQXOGYrV14iRt8NrE68LJqEhB9-6kzCVQ5_s1JKkyLCeobGhQGLROLF5GMX6bznr67sivmLfuFpA", "width": 4032}], "place_id": "ChIJGzE9DS1l44kRoOhiASS_fHg", "reference": "ChIJGzE9DS1l44kRoOhiASS_fHg", "scope": "GOOGLE", "types": ["locality", "political"], "vicinity": "Boston"}}