{"ChIJcymhGs1-44kRHtKvBdUOlsw": {"geometry": {"location": {"lat": 42.28698269999999, "lng": -71.13034569999999}, "viewport": {"northeast": {"lat": 42.2883344302915, "lng": -71.12899811970848}, "southwest": {"lat": 42.2856364697085, "lng": -71.13169608029149}}}, "icon": "https://maps.gstatic.com/mapfiles/place_api/icons/geocode-71.png", "id": "bf496a2cde393d206daaadd2d3a88bb04de40152", "name": "13-31 Belgrade Ave", "place_id": "ChIJcymhGs1-44kRHtKvBdUOlsw", "reference": "ChIJcymhGs1-44kRHtKvBdUOlsw", "scope": "GOOGLE", "types": ["route"], "vicinity": "Boston"}, "ChIJEaH34Mx-44kRCbAq1MsOZCs": {"geometry": {"location": {"lat": 42.28690510000001, "lng": -71.1302451}, "viewport": {"northeast": {"lat": 42.28830033029151, "lng": -71.1289229697085}, "southwest": {"lat": 42.28560236970851, "lng": -71.1316209302915}}}, "icon": "https://maps.gstatic.com/mapfiles/place_api/icons/shopping-71.png", "id": "14b2a6d5d308c52faadde5b81aab2942e4e52d3a", "name": "Futura Productions Inc", "photos": [{"height": 2592, "html_attributions": ["<a href=\"https://maps.google.com/maps/contrib/104206832554176826792/photos\">Futura Productions</a>"], "photo_reference": "CmRaAAAACi_bmaStXDJIBVzaAABjwHpyoE5rfpnNiZYiQNWk99SNF5eCcv5hpRqz2LQRAeS_gHUUsfhtfh0HosxDlsSnUBqmJ5raRvww0jhzRa6pMhbjg1H7N2D48b1smae_8XxvEhDLoZOwMkG5PRo-a_my-qgbGhQKB1YlbZop31B6wwsEATUwMgcQoA", "width": 3872}], "place_id": "ChIJEaH34Mx-44kRCbAq1MsOZCs", "plus_code": {"compound_code": "7VP9+QW Boston, Massachusetts, United States", "global_code": "87JC7VP9+QW"}, "rating": 5, "reference": "ChIJEaH34Mx-44kRCbAq1MsOZCs", "scope": "GOOGLE", "types": ["electronics_store", "home_goods_store", "store", "point_of_interest", "establishment"], "user_ratings_total": 10, "vicinity": "4 Belgrade Avenue, Roslindale"}, "ChIJBV_HBM1-44kR4KHzlM-WcFs": {"geometry": {"location": {"lat": 42.2867819, "lng": -71.1303738}, "viewport": {"northeast": {"lat": 42.2880589802915, "lng": -71.12910321970848}, "southwest": {"lat": 42.2853610197085, "lng": -71.1318011802915}}}, "icon": "https://maps.gstatic.com/mapfiles/place_api/icons/generic_business-71.png", "id": "8ca43ecc5298a14e18ca5fb80e67861fe08d969e", "name": "Sebastian's Barber Shop", "opening_hours": {"open_now": true}, "photos": [{"height": 382, "html_attributions": ["<a href=\"https://maps.google.com/maps/contrib/115619465986276219224/photos\">Sebastian&#39;s Barber Shop</a>"], "photo_reference": "CmRaAAAAfjN74iIHbWBIyGeNTD--0qxoXMtRWV_DF9HrQ8ojFk_FsP5Oi8dYxj8NPXc86cu9FXWJcgaJpLlauNEqUOO9cQRWcA3bp_ewuAtJpbZ8ohnSM7Lm4P-6bwnScuHRT21IEhDO8_I8ZYNSMXtN88pQ0-VdGhR98jUPT4PChzgzz8VcLnTCR-yY9A", "width": 512}], "place_id": "ChIJBV_HBM1-44kR4KHzlM-WcFs", "plus_code": {"compound_code": "7VP9+PV Boston, Massachusetts, United States", "global_code": "87JC7VP9+PV"}, "rating": 4.4, "reference": "ChIJBV_HBM1-44kR4KHzlM-WcFs", "scope": "GOOGLE", "types": ["beauty_salon", "hair_care", "health", "point_of_interest", "establishment"], "user_ratings_total": 45, "vicinity": "6 Corinth Street, Roslindale"}, "ChIJXwC14cx-44kRYvJbf0J4K-U": {"geometry": {"location": {"lat": 42.28672900000001, "lng": -71.130366}, "viewport": {"northeast": {"lat": 42.2881823802915, "lng": -71.1290776197085}, "southwest": {"lat": 42.2854844197085, "lng": -71.1317755802915}}}, "icon": "https://maps.gstatic.com/mapfiles/place_api/icons/generic_business-71.png", "id": "f03007e0ab3f1092eb0674df3c3199759e4ecdfa", "name": "Centre Cuts", "opening_hours": {"open_now": true}, "place_id": "ChIJXwC14cx-44kRYvJbf0J4K-U", "plus_code": {"compound_code": "7VP9+MV Boston, Massachusetts, United States", "global_code": "87JC7VP9+MV"}, "rating": 4.6, "reference": "ChIJXwC14cx-44kRYvJbf0J4K-U", "scope": "GOOGLE", "types": ["beauty_salon", "point_of_interest", "establishment"], "user_ratings_total": 18, "vicinity": "6 Belgrade Avenue, Roslindale"}, "ChIJ4eZZrc1-44kRBoU4009VUy8": {"geometry": {"location": {"lat": 42.2867863, "lng": -71.1303226}, "viewport": {"northeast": {"lat": 42.2882212802915, "lng": -71.1290235197085}, "southwest": {"lat": 42.2855233197085, "lng": -71.1317214802915}}}, "icon": "https://maps.gstatic.com/mapfiles/place_api/icons/shopping-71.png", "id": "05d7c789e06545c743ccb12108ed65a8a84b58e0", "name": "Appliance Standards Awareness", "place_id": "ChIJ4eZZrc1-44kRBoU4009VUy8", "plus_code": {"compound_code": "7VP9+PV Boston, Massachusetts, United States", "global_code": "87JC7VP9+PV"}, "reference": "ChIJ4eZZrc1-44kRBoU4009VUy8", "scope": "GOOGLE", "types": ["home_goods_store", "store", "point_of_interest", "establishment"], "vicinity": "20 Belgrade Avenue, Roslindale"}, "ChIJGdygL0J544kR8rd_HquXOmY": {"geometry": {"location": {"lat": 42.2868136, "lng": -71.1304628}, "viewport": {"northeast": {"lat": 42.2882182802915, "lng": -71.1291461197085}, "southwest": {"lat": 42.2855203197085, "lng": -71.1318440802915}}}, "icon": "https://maps.gstatic.com/mapfiles/place_api/icons/school-71.png", "id": "8cb78d109e72525950a11fdd665c92bb8e7fa027", "name": "Intra Yoga Therapy", "opening_hours": {"open_now": true}, "photos": [{"height": 2048, "html_attributions": ["<a href=\"https://maps.google.com/maps/contrib/104479218953935592383/photos\">Intra Yoga Therapy</a>"], "photo_reference": "CmRaAAAAL4bjfmEh1TUr_bpHLzn8BlrsH1Sd9zPWtB0XUKMs3TvTlv8eCI7NGOCa_Hd8dDwBNgNHnkU58scWUaI8iTqownfKQbtSV93DOI-c7dMbDpGZRL9kDqN_B_2urYaeHnrWEhDqFfg6brFfjwyN2UbuoJ68GhSJvb6pKtywukD1wJms-CNLQQZ8TQ", "width": 1530}], "place_id": "ChIJGdygL0J544kR8rd_HquXOmY", "plus_code": {"compound_code": "7VP9+PR Boston, Massachusetts, United States", "global_code": "87JC7VP9+PR"}, "rating": 5, "reference": "ChIJGdygL0J544kR8rd_HquXOmY", "scope": "GOOGLE", "types": ["gym", "health", "point_of_interest", "establishment"], "user_ratings_total": 3, "vicinity": "20 Belgrade Avenue #4, Roslindale"}, "ChIJnZYqBc1-44kRBwHkwaWwfJ4": {"geometry": {"location": {"lat": 42.28678399999999, "lng": -71.13055899999999}, "viewport": {"northeast": {"lat": 42.28819173029149, "lng": -71.1292373197085}, "southwest": {"lat": 42.28549376970849, "lng": -71.1319352802915}}}, "icon": "https://maps.gstatic.com/mapfiles/place_api/icons/generic_business-71.png", "id": "75f9a54d381bc75da6d94bcfc835ccafadfb3b50", "name": "musiConnects", "photos": [{"height": 1360, "html_attributions": ["<a href=\"https://maps.google.com/maps/contrib/102897380604304060767/photos\">musiConnects</a>"], "photo_reference": "CmRaAAAAny-Bcze9A_D8wjFtOKfAQpZw2YT0ruNaxU1ukMUN_VI2iKETzJbSlqCRVwjdWIkOjjAB8IKZGnSJGtid4CMMEHGwRVufySOn2rVJPZuHkVUjeGBjTtKmuzc6nc5XzOs-EhAlu1X40tdGHox3Rnm6KaLQGhRzVZRk879xKwrpE3unlGp3zhTJ4g", "width": 2048}], "place_id": "ChIJnZYqBc1-44kRBwHkwaWwfJ4", "plus_code": {"compound_code": "7VP9+PQ Boston, Massachusetts, United States", "global_code": "87JC7VP9+PQ"}, "reference": "ChIJnZYqBc1-44kRBwHkwaWwfJ4", "scope": "GOOGLE", "types": ["point_of_interest", "establishment"], "vicinity": "20 Belgrade Avenue, Roslindale"}, "ChIJYwuciw9644kRbbc1UhUsE6w": {"geometry": {"location": {"lat": 42.286851, "lng": -71.130267}, "viewport": {"northeast": {"lat": 42.2882661302915, "lng": -71.12895641970849}, "southwest": {"lat": 42.2855681697085, "lng": -71.1316543802915}}}, "icon": "https://maps.gstatic.com/mapfiles/place_api/icons/shopping-71.png", "id": "d0b0141b54176474b72fefba25bd301036c9a501", "name": "Futura Productions", "opening_hours": {"open_now": true}, "photos": [{"height": 2592, "html_attributions": ["<a href=\"https://maps.google.com/maps/contrib/110423211746693574448/photos\">Futura Productions</a>"], "photo_reference": "CmRaAAAAAu-ylDuL6wGMhw6XlGkRaILms4SFGHaFzWQFrX1P-ulIMEARyfSEJiOdafjcqgU5eEaX5Qftba-JEsYI-Qu2aR3KfWwYSyfENjCMDO7iF6Y8H-BK2Fho_RW_xHVhcZ-6EhD5PeE7B5MWuImQbeMmg8j4GhRzdGcLAz_WVIcVSOPpkhYlYP-MgQ", "width": 3872}], "place_id": "ChIJYwuciw9644kRbbc1UhUsE6w", "plus_code": {"compound_code": "7VP9+PV Boston, Massachusetts, United States", "global_code": "87JC7VP9+PV"}, "rating": 5, "reference": "ChIJYwuciw9644kRbbc1UhUsE6w", "scope": "GOOGLE", "types": ["electronics_store", "home_goods_store", "store", "point_of_interest", "establishment"], "user_ratings_total": 2, "vicinity": "4 Belgrade Avenue, Roslindale"}, "ChIJEaH34Mx-44kREJWKFUortfE": {"geometry": {"location": {"lat": 42.286734, "lng": -71.13030300000001}, "viewport": {"northeast": {"lat": 42.28806043029149, "lng": -71.1289203697085}, "southwest": {"lat": 42.2853624697085, "lng": -71.1316183302915}}}, "icon": "https://maps.gstatic.com/mapfiles/place_api/icons/generic_business-71.png", "id": "d2b7a54d66f681937f83bd9861645e62fbd6f195", "name": "Richard Alvord Architects", "opening_hours": {"open_now": true}, "place_id": "ChIJEaH34Mx-44kREJWKFUortfE", "plus_code": {"compound_code": "7VP9+MV Boston, Massachusetts, United States", "global_code": "87JC7VP9+MV"}, "reference": "ChIJEaH34Mx-44kREJWKFUortfE", "scope": "GOOGLE", "types": ["point_of_interest", "establishment"], "vicinity": "9 Birch Street # 4, Roslindale"}, "ChIJ01ibBM1-44kRuRsSVjTnc50": {"geometry": {"location": {"lat": 42.286653, "lng": -71.1303928}, "viewport": {"northeast": {"lat": 42.2879725302915, "lng": -71.12907591970848}, "southwest": {"lat": 42.28527456970851, "lng": -71.1317738802915}}}, "icon": "https://maps.gstatic.com/mapfiles/place_api/icons/generic_business-71.png", "id": "c4d0189f67ca1c4e1dd85dff3a9df71c23d3f449", "name": "Threading for Beauty", "opening_hours": {"open_now": true}, "photos": [{"height": 865, "html_attributions": ["<a href=\"https://maps.google.com/maps/contrib/110587688880435899434/photos\">Threading for Beauty</a>"], "photo_reference": "CmRaAAAAjdgI91akBDmPeLYVNrm4SLDJMnxYsWPiPEX3v8EO1szkdTln5ont5sMdGYy2XqJtDC-cRIctYg_QnQAfC4YAH-ENvGEsMcnMonNYa9N_TDPwTM_jy-OMs6c7DwtmahgjEhAWL3aJ19tTiy4QwUiTWWPVGhR6uzfuysfNw66k3kdk75hLT-mVoA", "width": 1536}], "place_id": "ChIJ01ibBM1-44kRuRsSVjTnc50", "plus_code": {"compound_code": "7VP9+MR Boston, Massachusetts, United States", "global_code": "87JC7VP9+MR"}, "rating": 5, "reference": "ChIJ01ibBM1-44kRuRsSVjTnc50", "scope": "GOOGLE", "types": ["beauty_salon", "hair_care", "point_of_interest", "establishment"], "user_ratings_total": 43, "vicinity": "8 Corinth Street, Boston"}, "ChIJYwk4G81-44kRklc5V0ggeyY": {"geometry": {"location": {"lat": 42.2868136, "lng": -71.1304628}, "viewport": {"northeast": {"lat": 42.2882182802915, "lng": -71.1291461197085}, "southwest": {"lat": 42.2855203197085, "lng": -71.1318440802915}}}, "icon": "https://maps.gstatic.com/mapfiles/place_api/icons/generic_business-71.png", "id": "bd6c40fe3c1803b5e1d5a5dfa4f02872e642c3d9", "name": "Raven Seltzer, L. Ac.", "place_id": "ChIJYwk4G81-44kRklc5V0ggeyY", "plus_code": {"compound_code": "7VP9+PR Boston, Massachusetts, United States", "global_code": "87JC7VP9+PR"}, "reference": "ChIJYwk4G81-44kRklc5V0ggeyY", "scope": "GOOGLE", "types": ["health", "point_of_interest", "establishment"], "vicinity": "20 Belgrade Avenue, Boston"}, "ChIJYwk4G81-44kRT1V9FY1WM8M": {"geometry": {"location": {"lat": 42.2868136, "lng": -71.1304628}, "viewport": {"northeast": {"lat": 42.2882182802915, "lng": -71.1291461197085}, "southwest": {"lat": 42.2855203197085, "lng": -71.1318440802915}}}, "icon": "https://maps.gstatic.com/mapfiles/place_api/icons/generic_business-71.png", "id": "b0726ff8d0fd062964f3bd5c1c2063145ac228d0", "name": "boston wellness center", "place_id": "ChIJYwk4G81-44kRT1V9FY1WM8M", "plus_code": {"compound_code": "7VP9+PR Boston, Massachusetts, United States", "global_code": "87JC7VP9+PR"}, "reference": "ChIJYwk4G81-44kRT1V9FY1WM8M", "scope": "GOOGLE", "types": ["point_of_interest", "establishment"], "vicinity": "20 Belgrade Avenue, Boston"}, "ChIJYwk4G81-44kR-HIIBVhaVTc": {"geometry": {"location": {"lat": 42.2868136, "lng": -71.1304628}, "viewport": {"northeast": {"lat": 42.2882182802915, "lng": -71.1291461197085}, "southwest": {"lat": 42.2855203197085, "lng": -71.1318440802915}}}, "icon": "https://maps.gstatic.com/mapfiles/place_api/icons/generic_business-71.png", "id": "c4df6c7163f0830d38da3f50516bd80260c2640a", "name": "Rachel Stanton, LICSW", "opening_hours": {"open_now": false}, "photos": [{"height": 2299, "html_attributions": ["<a href=\"https://maps.google.com/maps/contrib/101177806600024579975/photos\">Rachel Stanton, LICSW</a>"], "photo_reference": "CmRaAAAAugGEPHqjC5CnSBF6O309zDv_algECzofNEKRxqzMhvA4-OOFvYf6EZRzKlX2w89fkLB0uuNq-n5aPw1cJ_wZl5K8ERzPxqGtqL-1kp-WgfQfXIlw_Jxr3vZxLuqmnFwCEhApAxFt7TbaqakmyUn-L4IEGhSP3Z0aZABKntx2CcsyOdnx3pmOIQ", "width": 2910}], "place_id": "ChIJYwk4G81-44kR-HIIBVhaVTc", "plus_code": {"compound_code": "7VP9+PR Boston, Massachusetts, United States", "global_code": "87JC7VP9+PR"}, "reference": "ChIJYwk4G81-44kR-HIIBVhaVTc", "scope": "GOOGLE", "types": ["health", "point_of_interest", "establishment"], "vicinity": "20 Belgrade Avenue suite 5, Boston"}, "ChIJ6VgWmbJ_44kRzCPoXp71Lfo": {"geometry": {"location": {"lat": 42.2868136, "lng": -71.1304628}, "viewport": {"northeast": {"lat": 42.2882182802915, "lng": -71.1291461197085}, "southwest": {"lat": 42.2855203197085, "lng": -71.1318440802915}}}, "icon": "https://maps.gstatic.com/mapfiles/place_api/icons/school-71.png", "id": "a5d809b1202da520495da59d0cadad7bd57e1b2a", "name": "Beantown Babies", "photos": [{"height": 683, "html_attributions": ["<a href=\"https://maps.google.com/maps/contrib/113539658885592955953/photos\">Beantown Babies</a>"], "photo_reference": "CmRaAAAA71lVrsF0075kyHWENoNfodIj5AlKd2Cf06PKoOoKqOpJ6yZu5y5c7r6X9bBqb1swu5Z481VerGamGCQY_ozq0V83jzjH_7HY_2OoU43PU-066qY6R5WfGknuX2WgkV9DEhD4Ggr2EPsFpojHiWgPmudDGhSSGPy7wNtoMr-FEFLOA_aERFk0uQ", "width": 1024}], "place_id": "ChIJ6VgWmbJ_44kRzCPoXp71Lfo", "plus_code": {"compound_code": "7VP9+PR Boston, Massachusetts, United States", "global_code": "87JC7VP9+PR"}, "reference": "ChIJ6VgWmbJ_44kRzCPoXp71Lfo", "scope": "GOOGLE", "types": ["point_of_interest", "establishment"], "vicinity": "3098, 20 Belgrade Avenue #8, Boston"}, "ChIJ85B3K95_44kRTxRyWIhKbpQ": {"geometry": {"location": {"lat": 42.2868136, "lng": -71.1304628}, "viewport": {"northeast": {"lat": 42.2882182802915, "lng": -71.1291461197085}, "southwest": {"lat": 42.2855203197085, "lng": -71.1318440802915}}}, "icon": "https://maps.gstatic.com/mapfiles/place_api/icons/generic_business-71.png", "id": "870d75503bf781cbb5ff9a23a17605286670074b", "name": "Taylor Young Integrative Therapy & Yoga", "opening_hours": {"open_now": false}, "photos": [{"height": 1252, "html_attributions": ["<a href=\"https://maps.google.com/maps/contrib/116697574596699564377/photos\">Taylor Young Integrative Therapy &amp; Yoga</a>"], "photo_reference": "CmRaAAAAlO5YLQGWJnZZBG1t6RLwo-CRHjaPTKN__dqjVWNi38K9gahuPASbtXD-kLHfgBhGcDuc0OyDj7fVTDGyj2PUDcZe_BQbGdHnulwgKbqktC-wPDSjDTz2XmK54ABrI0oPEhBaTeiE3N_JiANyWHG1I0LQGhS_HWWCNaC8x185x1e8rQIzbAky6w", "width": 1249}], "place_id": "ChIJ85B3K95_44kRTxRyWIhKbpQ", "plus_code": {"compound_code": "7VP9+PR Boston, Massachusetts, United States", "global_code": "87JC7VP9+PR"}, "reference": "ChIJ85B3K95_44kRTxRyWIhKbpQ", "scope": "GOOGLE", "types": ["health", "point_of_interest", "establishment"], "vicinity": "20 Belgrade Avenue, Boston"}, "ChIJbdCs4Mx-44kRU_w_rS8ZiSo": {"geometry": {"location": {"lat": 42.28684320000001, "lng": -71.1303449}, "viewport": {"northeast": {"lat": 42.2882511802915, "lng": -71.12903016970849}, "southwest": {"lat": 42.28555321970851, "lng": -71.1317281302915}}}, "icon": "https://maps.gstatic.com/mapfiles/place_api/icons/generic_business-71.png", "id": "97d12ee8cd09dcef6bd7f68a06f19beb8f7ce015", "name": "Platt Anderson Freeman Architects (PAF)", "opening_hours": {"open_now": true}, "place_id": "ChIJbdCs4Mx-44kRU_w_rS8ZiSo", "plus_code": {"compound_code": "7VP9+PV Boston, Massachusetts, United States", "global_code": "87JC7VP9+PV"}, "reference": "ChIJbdCs4Mx-44kRU_w_rS8ZiSo", "scope": "GOOGLE", "types": ["point_of_interest", "establishment"], "vicinity": "4 Belgrade Avenue, Boston"}, "ChIJadV8HM1-44kRizsBRcd3UQ8": {"geometry": {"location": {"lat": 42.2869074, "lng": -71.13032299999999}, "viewport": {"northeast": {"lat": 42.2882912302915, "lng": -71.12899421970849}, "southwest": {"lat": 42.2855932697085, "lng": -71.1316921802915}}}, "icon": "https://maps.gstatic.com/mapfiles/place_api/icons/generic_business-71.png", "id": "d94c09f95c3eee3ca6545ddc0bcf17fe07291a3e", "name": "Platt Anderson Freeman Architects", "place_id": "ChIJadV8HM1-44kRizsBRcd3UQ8", "plus_code": {"compound_code": "7VP9+QV Boston, Massachusetts, United States", "global_code": "87JC7VP9+QV"}, "reference": "ChIJadV8HM1-44kRizsBRcd3UQ8", "scope": "GOOGLE", "types": ["point_of_interest", "establishment"], "vicinity": "10 Belgrade Avenue, Boston"}, "ChIJGzE9DS1l44kRoOhiASS_fHg": {"geometry": {"location": {"lat": 42.3600825, "lng": -71.0588801}, "viewport": {"northeast": {"lat": 42.40081989999999, "lng": -70.749455}, "southwest": {"lat": 42.22788, "lng": -71.191113}}}, "icon": "https://maps.gstatic.com/mapfiles/place_api/icons/geocode-71.png", "id": "06755c25d2b34d13942a4713971756a55b870ced", "name": "Boston", "photos": [{"height": 3024, "html_attributions": ["<a href=\"https://maps.google.com/maps/contrib/104670289779338733432/photos\">Natalia Zalucean</a>"], "photo_reference": "CmRaAAAAey6gOwy4K0OMHSG-RVbzceupTf3YljzJG6AfzlbyvDWpoFncg72ZIe1hZYLjO9vssXAhISkpNIAoQufm_Q82MHmsQiCGkJooJeWKc3iBW1cPFp_Cha3mMkKD4OiYwGXdEhD_MKSdY-qo3QU9RJXAVsXIGhR3S8LlhmfeeNl4SdhVhhTHRtNksQ", "width": 4032}], "place_id": "ChIJGzE9DS1l44kRoOhiASS_fHg", "reference": "ChIJGzE9DS1l44kRoOhiASS_fHg", "scope": "GOOGLE", "types": ["locality", "political"], "vicinity": "Boston"}}